{
  "analysis_metadata": {
    "name": "WinHttpAutoProxySvc",
    "filepath": "C:\\WINDOWS\\system32\\winhttp.dll",
    "time": 11.302389860153198,
    "termination_reason": "SUCCESS"
  },
  "analysis_result": {
    "auth_registration": [],
    "interface_registration": [
      {
        "arguments": {
          "Flags": [
            {
              "RPC_IF_ALLOW_CALLBACKS_WITH_NO_AUTH": false,
              "RPC_IF_ALLOW_LOCAL_ONLY": true,
              "RPC_IF_ALLOW_SECURE_ONLY": true,
              "RPC_IF_ALLOW_UNKNOWN_AUTHORITY": false,
              "RPC_IF_ASYNC_CALLBACK": false,
              "RPC_IF_AUTOLISTEN": true,
              "RPC_IF_OLE": false,
              "RPC_IF_SEC_CACHE_PER_PROC": false,
              "RPC_IF_SEC_NO_CACHE": false
            }
          ],
          "IfCallback": [
            0
          ],
          "IfSpec": [
            {
              "address": 6276062640,
              "flags": 100663296,
              "procedure_addresses": [
                {
                  "address": 6275358496,
                  "name": "GetProxyForUrl"
                },
                {
                  "address": 6275494800,
                  "name": "ResetAutoProxy"
                },
                {
                  "address": 6275770832,
                  "name": "SaveProxyCredentials"
                },
                {
                  "address": 6275771616,
                  "name": "StoreSavedProxyCredentialsForCurrentUser"
                },
                {
                  "address": 6275770144,
                  "name": "DeleteSavedProxyCredentials"
                },
                {
                  "address": 6275770592,
                  "name": "ReindicateAllProxies"
                },
                {
                  "address": 6275318928,
                  "name": "ReadProxySettings"
                },
                {
                  "address": 6275772704,
                  "name": "WriteProxySettings"
                },
                {
                  "address": 6275771376,
                  "name": "SetProxySettingsPerUser"
                },
                {
                  "address": 6275518912,
                  "name": "ConnectionUpdateIfIndexTable"
                },
                {
                  "address": 6275769696,
                  "name": "ConnectionSetPolicyEntries"
                },
                {
                  "address": 6275769264,
                  "name": "ConnectionDeletePolicyEntries"
                }
              ],
              "struct_values": {
                "DefaultManagerEpv": 0,
                "DispatchTable": 6276071136,
                "Flags": 100663296,
                "InterfaceId": {
                  "SyntaxGUID": {
                    "Data1": 880008525,
                    "Data2": 11912,
                    "Data3": 16390,
                    "Data4": [
                      "9c",
                      "ba",
                      "22",
                      "57",
                      "09",
                      "09",
                      "dd",
                      "10"
                    ]
                  },
                  "SyntaxVersion": {
                    "MajorVersion": 5,
                    "MinorVersion": 1
                  }
                },
                "InterpreterInfo": 6276071040,
                "Length": 96,
                "RpcProtseqEndpoint": 0,
                "RpcProtseqEndpointCount": 0,
                "TransferSyntax": {
                  "SyntaxGUID": {
                    "Data1": 2324192516,
                    "Data2": 7403,
                    "Data3": 4553,
                    "Data4": [
                      "9f",
                      "e8",
                      "08",
                      "00",
                      "2b",
                      "10",
                      "48",
                      "60"
                    ]
                  },
                  "SyntaxVersion": {
                    "MajorVersion": 2,
                    "MinorVersion": 0
                  }
                }
              },
              "uuid": {
                "uuid": "3473DD4D-2E88-4006-9CBA-22570909DD10",
                "version": "5.1"
              }
            }
          ],
          "MaxCalls": [
            1234
          ],
          "MaxRpcSize": [
            4294967295
          ],
          "MgrEpv": [
            0
          ],
          "MgrTypeUuid": [
            0
          ],
          "SecurityDescriptor": [
            6276093184
          ],
          "api_function": "RpcServerRegisterIf3",
          "possible_clients": {
            "0": [
              {
                "call_attributes": [
                  {
                    "AuthenticationLevel": 7,
                    "IsClientLocal": 1,
                    "protseq_string": "ncacn_np"
                  },
                  {
                    "AuthenticationLevel": 1,
                    "IsClientLocal": 1,
                    "protseq_string": "ncacn_np"
                  },
                  {
                    "AuthenticationLevel": 5,
                    "IsClientLocal": 1,
                    "protseq_string": "ncacn_np"
                  },
                  {
                    "AuthenticationLevel": 4,
                    "IsClientLocal": 1,
                    "protseq_string": "ncacn_np"
                  },
                  {
                    "AuthenticationLevel": 6,
                    "IsClientLocal": 1,
                    "protseq_string": "ncacn_np"
                  },
                  {
                    "AuthenticationLevel": 2,
                    "IsClientLocal": 1,
                    "protseq_string": "ncacn_np"
                  },
                  {
                    "AuthenticationLevel": 3,
                    "IsClientLocal": 1,
                    "protseq_string": "ncacn_np"
                  },
                  {
                    "AuthenticationLevel": 3,
                    "IsClientLocal": 1,
                    "protseq_string": "ncalrpc"
                  },
                  {
                    "AuthenticationLevel": 1,
                    "IsClientLocal": 1,
                    "protseq_string": "ncalrpc"
                  },
                  {
                    "AuthenticationLevel": 5,
                    "IsClientLocal": 1,
                    "protseq_string": "ncalrpc"
                  },
                  {
                    "AuthenticationLevel": 4,
                    "IsClientLocal": 1,
                    "protseq_string": "ncalrpc"
                  },
                  {
                    "AuthenticationLevel": 2,
                    "IsClientLocal": 1,
                    "protseq_string": "ncalrpc"
                  },
                  {
                    "AuthenticationLevel": 6,
                    "IsClientLocal": 1,
                    "protseq_string": "ncalrpc"
                  },
                  {
                    "AuthenticationLevel": 7,
                    "IsClientLocal": 1,
                    "protseq_string": "ncalrpc"
                  }
                ],
                "extra_constraints": []
              }
            ]
          }
        },
        "callsite_address": 6275762372
      },
      {
        "arguments": {
          "Flags": [
            {
              "RPC_IF_ALLOW_CALLBACKS_WITH_NO_AUTH": false,
              "RPC_IF_ALLOW_LOCAL_ONLY": true,
              "RPC_IF_ALLOW_SECURE_ONLY": true,
              "RPC_IF_ALLOW_UNKNOWN_AUTHORITY": false,
              "RPC_IF_ASYNC_CALLBACK": false,
              "RPC_IF_AUTOLISTEN": true,
              "RPC_IF_OLE": false,
              "RPC_IF_SEC_CACHE_PER_PROC": false,
              "RPC_IF_SEC_NO_CACHE": false
            }
          ],
          "IfCallback": [
            0
          ],
          "IfSpec": [
            {
              "address": {
                "annotations": [
                  "<DefinitionAnnotation(<Definition {Atom:<Reg 24<8>>, Codeloc:<0x17613dc36 id=0x17613dc1b[30] contextless>}>)"
                ],
                "bitvector": "<BV64 TOP>"
              },
              "flags": null,
              "procedure_addresses": null,
              "struct_values": null,
              "uuid": null
            }
          ],
          "MaxCalls": [
            1234
          ],
          "MaxRpcSize": [
            4294967295
          ],
          "MgrEpv": [
            0
          ],
          "MgrTypeUuid": [
            0
          ],
          "SecurityDescriptor": [
            {
              "annotations": [
                "<DefinitionAnnotation(<Definition {Tags:{<LocalVariableTag {Metadata: {'tagged_by': 'SimEngineRDVEX._store_core', 'ins_addr': 6275980315}}>}, Atom:<Mem SP-0x40<8> (stack)>, Codeloc:<0x17613dc1b id=0x17613dc1b[4] contextless>}>)"
              ],
              "bitvector": "<BV64 TOP>"
            }
          ],
          "api_function": "RpcServerRegisterIf3",
          "possible_clients": {
            "0": [
              {
                "call_attributes": [
                  {
                    "AuthenticationLevel": 7,
                    "IsClientLocal": 1,
                    "protseq_string": "ncalrpc"
                  },
                  {
                    "AuthenticationLevel": 1,
                    "IsClientLocal": 1,
                    "protseq_string": "ncacn_np"
                  },
                  {
                    "AuthenticationLevel": 5,
                    "IsClientLocal": 1,
                    "protseq_string": "ncacn_np"
                  },
                  {
                    "AuthenticationLevel": 4,
                    "IsClientLocal": 1,
                    "protseq_string": "ncacn_np"
                  },
                  {
                    "AuthenticationLevel": 6,
                    "IsClientLocal": 1,
                    "protseq_string": "ncacn_np"
                  },
                  {
                    "AuthenticationLevel": 2,
                    "IsClientLocal": 1,
                    "protseq_string": "ncacn_np"
                  },
                  {
                    "AuthenticationLevel": 3,
                    "IsClientLocal": 1,
                    "protseq_string": "ncacn_np"
                  },
                  {
                    "AuthenticationLevel": 3,
                    "IsClientLocal": 1,
                    "protseq_string": "ncalrpc"
                  },
                  {
                    "AuthenticationLevel": 1,
                    "IsClientLocal": 1,
                    "protseq_string": "ncalrpc"
                  },
                  {
                    "AuthenticationLevel": 5,
                    "IsClientLocal": 1,
                    "protseq_string": "ncalrpc"
                  },
                  {
                    "AuthenticationLevel": 4,
                    "IsClientLocal": 1,
                    "protseq_string": "ncalrpc"
                  },
                  {
                    "AuthenticationLevel": 2,
                    "IsClientLocal": 1,
                    "protseq_string": "ncalrpc"
                  },
                  {
                    "AuthenticationLevel": 6,
                    "IsClientLocal": 1,
                    "protseq_string": "ncalrpc"
                  },
                  {
                    "AuthenticationLevel": 7,
                    "IsClientLocal": 1,
                    "protseq_string": "ncacn_np"
                  }
                ],
                "extra_constraints": []
              }
            ]
          }
        },
        "callsite_address": 6275980315
      }
    ],
    "protseq_usage": [
      {
        "arguments": {
          "MaxCalls": [
            0
          ],
          "Protseq": [
            {
              "address": 6276087432,
              "string": "ncalrpc"
            }
          ],
          "SecurityDescriptor": [
            6276093184
          ],
          "api_function": "RpcServerUseProtseqW"
        },
        "callsite_address": 6275762300
      },
      {
        "arguments": {
          "MaxCalls": [
            0
          ],
          "Protseq": [
            {
              "address": 6276087432,
              "string": "ncalrpc"
            }
          ],
          "SecurityDescriptor": [
            6276093184
          ],
          "api_function": "RpcServerUseProtseqW"
        },
        "callsite_address": 6275762289
      },
      {
        "arguments": {
          "Endpoint": [
            {
              "address": {
                "annotations": [
                  "<DefinitionAnnotation(<Definition {Atom:<Reg 80<8>>, Codeloc:<0x17613dbc2 id=0x17613dbab[20] contextless>}>)"
                ],
                "bitvector": "<BV64 TOP>"
              },
              "string": null
            }
          ],
          "MaxCalls": [
            10
          ],
          "Protseq": [
            {
              "address": 6276087432,
              "string": "ncalrpc"
            }
          ],
          "SecurityDescriptor": [
            {
              "annotations": [
                "<DefinitionAnnotation(<Definition {Atom:<Reg 88<8>>, Codeloc:<0x17613dbb8 id=0x17613dbab[13] contextless>}>)"
              ],
              "bitvector": "<BV64 TOP>"
            }
          ],
          "api_function": "RpcServerUseProtseqEpW"
        },
        "callsite_address": 6275980216
      },
      {
        "arguments": {
          "Endpoint": [
            {
              "address": {
                "annotations": [
                  "<DefinitionAnnotation(<Definition {Atom:<Reg 80<8>>, Codeloc:<0x17613dbc2 id=0x17613dbab[20] contextless>}>)"
                ],
                "bitvector": "<BV64 TOP>"
              },
              "string": null
            }
          ],
          "MaxCalls": [
            10
          ],
          "Protseq": [
            {
              "address": 6276087432,
              "string": "ncalrpc"
            }
          ],
          "SecurityDescriptor": [
            {
              "annotations": [
                "<DefinitionAnnotation(<Definition {Atom:<Reg 88<8>>, Codeloc:<0x17613dbb8 id=0x17613dbab[13] contextless>}>)"
              ],
              "bitvector": "<BV64 TOP>"
            }
          ],
          "api_function": "RpcServerUseProtseqEpW"
        },
        "callsite_address": 6275980203
      }
    ],
    "rpc_constraints": {}
  }
}